toolbox/__init__.py
toolbox/dicom2image.py
toolbox/dicom2nifti.py
toolbox/image2nifti.py
toolbox/nifti2dicom.py
toolbox/nifti2image.py
formatconverter_medical-1.2.5.dist-info/LICENSE
formatconverter_medical-1.2.5.dist-info/METADATA
formatconverter_medical-1.2.5.dist-info/WHEEL
formatconverter_medical-1.2.5.dist-info/top_level.txt
formatconverter_medical-1.2.5.dist-info/RECORD
