Metadata-Version: 2.1
Name: formatconverter-medical
Version: 1.2.5
Summary: A toolbox for converting medical imaging data between DICOM, NIfTI, and image formats.
Home-page: https://github.com/cnnlabyzu/formatconverter
Author: Wei-Chun Kevin Tsai
Author-email: cnnlabproject@gmail.com
License-File: LICENSE
Requires-Dist: SimpleITK ==2.2.1
Requires-Dist: tqdm ==4.66.2
Requires-Dist: pydicom ==2.0.0
Requires-Dist: opencv-contrib-python ==4.9.0.80
Requires-Dist: numpy ==1.24.3
Requires-Dist: nibabel ==4.0.2
Requires-Dist: matplotlib ==3.5.3
